basic/user/src/count.v
module count(
input wire CLK,
input wire RSTn, // 异步复位
input wire LDn,
input wire E,
input [5:0]PD,
output wire [5:0]QT,
output wire RCO
);
reg [5:0] SQ;
assign RCO = ~SQ[5] & ~SQ[4] & ~SQ[3] & ~SQ[2] & ~SQ[1] & ~SQ[0];
assign QT = SQ;
always @(posedge CLK or negedge RSTn) begin // 异步复位
    if(!RSTn) 
        SQ <= 0; // 复位时清零
    else if(!LDn) 
        SQ <= PD;
    else if(E) begin
        if(SQ == 0) 
            SQ <= PD;
        else 
            SQ <= SQ - 1;
    end
end
endmodule

basic/user/src/control.v
module control(
input wire CLK,
input wire RSTn,
input wire AS,//北方向为1
input wire BS,
input wire T3,//定时器完成
input wire T27,
input wire [5:0]SD3,//定时器数值
input wire [5:0]SD27,
output wire C3,//计数器使能信号
output wire C27,
output wire LD3n,//加载数据使能信号
output wire LD27n,
output wire [1:0]state,//状态
output wire [5:0]A_time,//A方向数值
output wire [5:0]B_time,//B方向数值
output wire [5:0]led//输出灯
);
parameter Y_time = 6'd3;//黄灯时间
parameter [1:0]S0=2'b00,S1=2'b01,S2=2'b10,S3=2'b11;

// LED位定义
parameter RED_A = 5, YELLOW_A = 4, GREEN_A = 3;
parameter RED_B = 2, YELLOW_B = 1, GREEN_B = 0;

reg [1:0]cur_state,next_state;
reg [5:0]control_led,control_A_time,control_B_time;
reg control_C3,control_C27;
reg control_LD3n,control_LD27n;
wire AK,BK;
assign AK = BS & (T27 | ~AS);
assign BK = ~BS | AS & T27;
assign state = cur_state;
assign led = control_led;
assign A_time = control_A_time;
assign B_time = control_B_time;
assign C3 = control_C3;
assign C27 = control_C27;
assign LD3n = control_LD3n;
assign LD27n = control_LD27n;

always @(*) begin
    case(cur_state)
    S0:if(AK) next_state = S1;
        else next_state = S0;
    S1:if(T3) next_state = S2;
        else next_state = S1;
    S2:if(BK) next_state = S3;
        else next_state = S2;
    S3:if(T3) next_state = S0;
        else next_state = S3;
    default: next_state = S0;
    endcase
end

always @(posedge CLK or negedge RSTn) begin
    if(!RSTn) cur_state <= S0;
    else cur_state <= next_state;
end

always @(*) begin
    if(!RSTn) begin
        control_led = (1 << GREEN_A) | (1 << RED_B); // A绿 B红
        control_LD27n = 1'b0;
        control_C27 = 1'b1;
        control_C3 = 1'b0;
        control_A_time = 6'd0;
        control_B_time = 6'd0;
    end
    else begin
    case(cur_state)
    S0:begin  // A绿 B红
        control_C27 = 1'b1;
        control_LD27n = 1'b1;
        control_C3 = 1'b0;
        control_LD3n = 1'b0;
        control_A_time = SD27;
        control_B_time = SD27 + Y_time;
        control_led = (1 << GREEN_A) | (1 << RED_B);
    end
    S1:begin  // A黄 B红
        control_C27 = 1'b0;
        control_LD27n = 1'b0;
        control_C3 = 1'b1;
        control_LD3n = 1'b1;
        control_A_time = SD3;
        control_B_time = SD3;
        control_led = (1 << YELLOW_A) | (1 << RED_B);
    end
    S2:begin  // A红 B绿
        control_C27 = 1'b1;
        control_LD27n = 1'b1;
        control_C3 = 1'b0;
        control_LD3n = 1'b0;
        control_A_time = SD27 + Y_time;
        control_B_time = SD27;
        control_led = (1 << RED_A) | (1 << GREEN_B);
    end
    S3:begin  // A红 B黄
        control_C27 = 1'b0;
        control_LD27n = 1'b0;
        control_C3 = 1'b1;
        control_LD3n = 1'b1;
        control_A_time = SD3;
        control_B_time = SD3;
        control_led = (1 << RED_A) | (1 << YELLOW_B);
    end
    default:begin
        control_C27 = 1'b0;
        control_LD27n = 1'b0;
        control_C3 = 1'b0;
        control_LD3n = 1'b0;
        control_A_time = 6'd0;
        control_B_time = 6'd0;
        control_led = (1 << GREEN_A) | (1 << RED_B);
    end
    endcase
end
end       
endmodule

basic/user/src/trafficlight.v
module trafficlight(
    input wire CLK,
    input wire RSTn,
    input wire AS,
    input wire BS,
    output wire [1:0] state,
    output wire [5:0] led,
    output wire [5:0] A_time,
    output wire [5:0] B_time
);
parameter Y_time = 6'd3;
parameter AG_time = 6'd27;
wire T3,T27;
wire C3,C27;
wire [5:0]SD3,SD27;
wire LD3n,LD27n;
control UC(
.CLK(CLK),
.RSTn(RSTn),
.AS(AS),
.BS(BS),
.T3(T3),
.T27(T27),
.SD3(SD3),
.SD27(SD27),
.C3(C3),
.C27(C27),
.LD3n(LD3n),
.LD27n(LD27n),
.state(state),
.A_time(A_time),
.B_time(B_time),
.led(led)
);
count UD3(
.CLK(CLK),
.RSTn(RSTn), // 异步复位
.LDn(LD3n),
.E(C3),
.PD(Y_time - 1'b1),
.QT(SD3),
.RCO(T3)
);
count UD27(
.CLK(CLK),
.RSTn(RSTn), // 异步复位
.LDn(LD27n),
.E(C27),
.PD(AG_time - 1'b1),
.QT(SD27),
.RCO(T27)
);
endmodule

basic/user/sim/trafficlight_tb.v
`timescale 1ns / 1ps

module trafficlight_tb();
    reg AS;
    reg BS;
    reg CLK;
    reg RSTn;
    wire [5:0] A_time;
    wire [5:0] B_time;
    wire [5:0] led;
    wire [1:0] state;

    trafficlight DUT(
        .CLK(CLK),
        .RSTn(RSTn),
        .AS(AS),
        .BS(BS),
        .state(state),
        .A_time(A_time),
        .B_time(B_time),
        .led(led)
    );
    initial begin
        $dumpfile("trafficlight_waveform.vcd");
        $dumpvars(0, trafficlight_tb);
    end
    initial begin 
        RSTn = 1'b0;
        #20 RSTn = 1'b1; // 延时复位
    end

    initial begin
        AS = 1'b1;
        #140 AS = 1'b0;
        #90 AS = 1'b1;
        #220 AS = 1'b0;
        #320 AS = 1'b1;
    end 

    initial begin
        BS = 1'b1;
        #230 BS = 1'b0;
        #110 BS = 1'b1;
        #110 BS = 1'b0;
        #170 BS = 1'b1;
    end

    always begin
        CLK = 1'b0;
        #5 CLK = 1'b1;
        #5;
    end 

    // 添加监控输出
    initial begin
        $monitor("Time=%t, State=%b, A_time=%d, B_time=%d, LED=%b", 
                 $time, state, A_time, B_time, led);
    end

    // ==========================================================
    // ==           在这里添加仿真结束的时间限制               ==
    // ==========================================================
    // 你的最后一个激励在 #320 发生，我们让仿真再多运行 50ns，然后结束。
    // 总仿真时间为 20 + 140 + 90 + 220 + 320 + 50 = 840ns
    initial begin
        #840; // 等待所有激励和响应完成
        $finish; // 明确地结束仿真
    end
    // ==========================================================

endmodule

basic/trafficlight_waveform.vcd
$date
	Tue Oct 07 01:45:18 2025
$end
$version
	Icarus Verilog
$end
$timescale
	1ps
$end
$scope module trafficlight_tb $end
$var wire 2 ! state [1:0] $end
$var wire 6 " led [5:0] $end
$var wire 6 # B_time [5:0] $end
$var wire 6 $ A_time [5:0] $end
$var reg 1 % AS $end
$var reg 1 & BS $end
$var reg 1 ' CLK $end
$var reg 1 ( RSTn $end
$scope module DUT $end
$var wire 1 % AS $end
$var wire 1 & BS $end
$var wire 1 ' CLK $end
$var wire 1 ( RSTn $end
$var wire 2 ) state [1:0] $end
$var wire 6 * led [5:0] $end
$var wire 1 + T3 $end
$var wire 1 , T27 $end
$var wire 6 - SD3 [5:0] $end
$var wire 6 . SD27 [5:0] $end
$var wire 1 / LD3n $end
$var wire 1 0 LD27n $end
$var wire 1 1 C3 $end
$var wire 1 2 C27 $end
$var wire 6 3 B_time [5:0] $end
$var wire 6 4 A_time [5:0] $end
$scope module UC $end
$var wire 1 5 AK $end
$var wire 1 % AS $end
$var wire 6 6 A_time [5:0] $end
$var wire 1 7 BK $end
$var wire 1 & BS $end
$var wire 6 8 B_time [5:0] $end
$var wire 1 2 C27 $end
$var wire 1 1 C3 $end
$var wire 1 ' CLK $end
$var wire 1 0 LD27n $end
$var wire 1 / LD3n $end
$var wire 1 ( RSTn $end
$var wire 6 9 led [5:0] $end
$var wire 2 : state [1:0] $end
$var wire 1 + T3 $end
$var wire 1 , T27 $end
$var wire 6 ; SD3 [5:0] $end
$var wire 6 < SD27 [5:0] $end
$var reg 6 = control_A_time [5:0] $end
$var reg 6 > control_B_time [5:0] $end
$var reg 1 ? control_C27 $end
$var reg 1 @ control_C3 $end
$var reg 1 A control_LD27n $end
$var reg 1 B control_LD3n $end
$var reg 6 C control_led [5:0] $end
$var reg 2 D cur_state [1:0] $end
$var reg 2 E next_state [1:0] $end
$upscope $end
$scope module UD27 $end
$var wire 1 ' CLK $end
$var wire 1 2 E $end
$var wire 1 0 LDn $end
$var wire 6 F PD [5:0] $end
$var wire 6 G QT [5:0] $end
$var wire 1 , RCO $end
$var wire 1 ( RSTn $end
$var reg 6 H SQ [5:0] $end
$upscope $end
$scope module UD3 $end
$var wire 1 ' CLK $end
$var wire 1 1 E $end
$var wire 1 / LDn $end
$var wire 6 I PD [5:0] $end
$var wire 6 J QT [5:0] $end
$var wire 1 + RCO $end
$var wire 1 ( RSTn $end
$var reg 6 K SQ [5:0] $end
$upscope $end
$upscope $end
$upscope $end
$enddefinitions $end
#0
$dumpvars
b0 K
b0 J
b10 I
b0 H
b0 G
b11010 F
b1 E
b0 D
b1100 C
xB
0A
0@
1?
b0 >
b0 =
b0 <
b0 ;
b0 :
b1100 9
b0 8
17
b0 6
15
b0 4
b0 3
12
01
00
x/
b0 .
b0 -
1,
1+
b1100 *
b0 )
0(
0'
1&
1%
b0 $
b0 #
b1100 "
b0 !
$end
#5000
1'
#10000
0'
#15000
1'
#20000
b11 #
b11 3
b11 8
b11 >
0/
0B
10
1A
0'
1(
#25000
07
05
0,
0+
b10100 "
b10100 *
b10100 9
b10100 C
b10 #
b10 3
b10 8
b10 >
b10 $
b10 4
b10 6
b10 =
1/
1B
11
1@
00
0A
02
0?
b1 E
b11010 .
b11010 <
b11010 G
b11010 H
b10 -
b10 ;
b10 J
b10 K
b1 !
b1 )
b1 :
b1 D
1'
#30000
0'
#35000
b1 #
b1 3
b1 8
b1 >
b1 $
b1 4
b1 6
b1 =
b1 -
b1 ;
b1 J
b1 K
1'
#40000
0'
#45000
b10 E
1+
b0 #
b0 3
b0 8
b0 >
b0 $
b0 4
b0 6
b0 =
b0 -
b0 ;
b0 J
b0 K
1'
#50000
0'
#55000
0+
b100001 "
b100001 *
b100001 9
b100001 C
b11010 #
b11010 3
b11010 8
b11010 >
b11101 $
b11101 4
b11101 6
b11101 =
0/
0B
01
0@
10
1A
12
1?
b10 !
b10 )
b10 :
b10 D
b10 -
b10 ;
b10 J
b10 K
1'
#60000
0'
#65000
b11001 #
b11001 3
b11001 8
b11001 >
b11100 $
b11100 4
b11100 6
b11100 =
b11001 .
b11001 <
b11001 G
b11001 H
1'
#70000
0'
#75000
b11000 #
b11000 3
b11000 8
b11000 >
b11011 $
b11011 4
b11011 6
b11011 =
b11000 .
b11000 <
b11000 G
b11000 H
1'
#80000
0'
#85000
b10111 #
b10111 3
b10111 8
b10111 >
b11010 $
b11010 4
b11010 6
b11010 =
b10111 .
b10111 <
b10111 G
b10111 H
1'
#90000
0'
#95000
b10110 #
b10110 3
b10110 8
b10110 >
b11001 $
b11001 4
b11001 6
b11001 =
b10110 .
b10110 <
b10110 G
b10110 H
1'
#100000
0'
#105000
b10101 #
b10101 3
b10101 8
b10101 >
b11000 $
b11000 4
b11000 6
b11000 =
b10101 .
b10101 <
b10101 G
b10101 H
1'
#110000
0'
#115000
b10100 #
b10100 3
b10100 8
b10100 >
b10111 $
b10111 4
b10111 6
b10111 =
b10100 .
b10100 <
b10100 G
b10100 H
1'
#120000
0'
#125000
b10011 #
b10011 3
b10011 8
b10011 >
b10110 $
b10110 4
b10110 6
b10110 =
b10011 .
b10011 <
b10011 G
b10011 H
1'
#130000
0'
#135000
b10010 #
b10010 3
b10010 8
b10010 >
b10101 $
b10101 4
b10101 6
b10101 =
b10010 .
b10010 <
b10010 G
b10010 H
1'
#140000
15
0'
0%
#145000
b10001 #
b10001 3
b10001 8
b10001 >
b10100 $
b10100 4
b10100 6
b10100 =
b10001 .
b10001 <
b10001 G
b10001 H
1'
#150000
0'
#155000
b10000 #
b10000 3
b10000 8
b10000 >
b10011 $
b10011 4
b10011 6
b10011 =
b10000 .
b10000 <
b10000 G
b10000 H
1'
#160000
0'
#165000
b1111 #
b1111 3
b1111 8
b1111 >
b10010 $
b10010 4
b10010 6
b10010 =
b1111 .
b1111 <
b1111 G
b1111 H
1'
#170000
0'
#175000
b1110 #
b1110 3
b1110 8
b1110 >
b10001 $
b10001 4
b10001 6
b10001 =
b1110 .
b1110 <
b1110 G
b1110 H
1'
#180000
0'
#185000
b1101 #
b1101 3
b1101 8
b1101 >
b10000 $
b10000 4
b10000 6
b10000 =
b1101 .
b1101 <
b1101 G
b1101 H
1'
#190000
0'
#195000
b1100 #
b1100 3
b1100 8
b1100 >
b1111 $
b1111 4
b1111 6
b1111 =
b1100 .
b1100 <
b1100 G
b1100 H
1'
#200000
0'
#205000
b1011 #
b1011 3
b1011 8
b1011 >
b1110 $
b1110 4
b1110 6
b1110 =
b1011 .
b1011 <
b1011 G
b1011 H
1'
#210000
0'
#215000
b1010 #
b1010 3
b1010 8
b1010 >
b1101 $
b1101 4
b1101 6
b1101 =
b1010 .
b1010 <
b1010 G
b1010 H
1'
#220000
0'
#225000
b1001 #
b1001 3
b1001 8
b1001 >
b1100 $
b1100 4
b1100 6
b1100 =
b1001 .
b1001 <
b1001 G
b1001 H
1'
#230000
b11 E
17
05
0'
1%
0&
#235000
b100010 "
b100010 *
b100010 9
b100010 C
b10 #
b10 3
b10 8
b10 >
b10 $
b10 4
b10 6
b10 =
1/
1B
11
1@
00
0A
02
0?
b11 !
b11 )
b11 :
b11 D
b1000 .
b1000 <
b1000 G
b1000 H
1'
#240000
0'
#245000
b1 #
b1 3
b1 8
b1 >
b1 $
b1 4
b1 6
b1 =
b11010 .
b11010 <
b11010 G
b11010 H
b1 -
b1 ;
b1 J
b1 K
1'
#250000
0'
#255000
b0 E
1+
b0 #
b0 3
b0 8
b0 >
b0 $
b0 4
b0 6
b0 =
b0 -
b0 ;
b0 J
b0 K
1'
#260000
0'
#265000
0+
b1100 "
b1100 *
b1100 9
b1100 C
b11101 #
b11101 3
b11101 8
b11101 >
b11010 $
b11010 4
b11010 6
b11010 =
0/
0B
01
0@
10
1A
12
1?
b10 -
b10 ;
b10 J
b10 K
b0 !
b0 )
b0 :
b0 D
1'
#270000
0'
#275000
b11100 #
b11100 3
b11100 8
b11100 >
b11001 $
b11001 4
b11001 6
b11001 =
b11001 .
b11001 <
b11001 G
b11001 H
1'
#280000
0'
#285000
b11011 #
b11011 3
b11011 8
b11011 >
b11000 $
b11000 4
b11000 6
b11000 =
b11000 .
b11000 <
b11000 G
b11000 H
1'
#290000
0'
#295000
b11010 #
b11010 3
b11010 8
b11010 >
b10111 $
b10111 4
b10111 6
b10111 =
b10111 .
b10111 <
b10111 G
b10111 H
1'
#300000
0'
#305000
b11001 #
b11001 3
b11001 8
b11001 >
b10110 $
b10110 4
b10110 6
b10110 =
b10110 .
b10110 <
b10110 G
b10110 H
1'
#310000
0'
#315000
b11000 #
b11000 3
b11000 8
b11000 >
b10101 $
b10101 4
b10101 6
b10101 =
b10101 .
b10101 <
b10101 G
b10101 H
1'
#320000
0'
#325000
b10111 #
b10111 3
b10111 8
b10111 >
b10100 $
b10100 4
b10100 6
b10100 =
b10100 .
b10100 <
b10100 G
b10100 H
1'
#330000
0'
#335000
b10110 #
b10110 3
b10110 8
b10110 >
b10011 $
b10011 4
b10011 6
b10011 =
b10011 .
b10011 <
b10011 G
b10011 H
1'
#340000
07
0'
1&
#345000
b10101 #
b10101 3
b10101 8
b10101 >
b10010 $
b10010 4
b10010 6
b10010 =
b10010 .
b10010 <
b10010 G
b10010 H
1'
#350000
0'
#355000
b10100 #
b10100 3
b10100 8
b10100 >
b10001 $
b10001 4
b10001 6
b10001 =
b10001 .
b10001 <
b10001 G
b10001 H
1'
#360000
0'
#365000
b10011 #
b10011 3
b10011 8
b10011 >
b10000 $
b10000 4
b10000 6
b10000 =
b10000 .
b10000 <
b10000 G
b10000 H
1'
#370000
0'
#375000
b10010 #
b10010 3
b10010 8
b10010 >
b1111 $
b1111 4
b1111 6
b1111 =
b1111 .
b1111 <
b1111 G
b1111 H
1'
#380000
0'
#385000
b10001 #
b10001 3
b10001 8
b10001 >
b1110 $
b1110 4
b1110 6
b1110 =
b1110 .
b1110 <
b1110 G
b1110 H
1'
#390000
0'
#395000
b10000 #
b10000 3
b10000 8
b10000 >
b1101 $
b1101 4
b1101 6
b1101 =
b1101 .
b1101 <
b1101 G
b1101 H
1'
#400000
0'
#405000
b1111 #
b1111 3
b1111 8
b1111 >
b1100 $
b1100 4
b1100 6
b1100 =
b1100 .
b1100 <
b1100 G
b1100 H
1'
#410000
0'
#415000
b1110 #
b1110 3
b1110 8
b1110 >
b1011 $
b1011 4
b1011 6
b1011 =
b1011 .
b1011 <
b1011 G
b1011 H
1'
#420000
0'
#425000
b1101 #
b1101 3
b1101 8
b1101 >
b1010 $
b1010 4
b1010 6
b1010 =
b1010 .
b1010 <
b1010 G
b1010 H
1'
#430000
0'
#435000
b1100 #
b1100 3
b1100 8
b1100 >
b1001 $
b1001 4
b1001 6
b1001 =
b1001 .
b1001 <
b1001 G
b1001 H
1'
#440000
0'
#445000
b1011 #
b1011 3
b1011 8
b1011 >
b1000 $
b1000 4
b1000 6
b1000 =
b1000 .
b1000 <
b1000 G
b1000 H
1'
#450000
17
0'
0&
0%
#455000
b1010 #
b1010 3
b1010 8
b1010 >
b111 $
b111 4
b111 6
b111 =
b111 .
b111 <
b111 G
b111 H
1'
#460000
0'
#465000
b1001 #
b1001 3
b1001 8
b1001 >
b110 $
b110 4
b110 6
b110 =
b110 .
b110 <
b110 G
b110 H
1'
#470000
0'
#475000
b1000 #
b1000 3
b1000 8
b1000 >
b101 $
b101 4
b101 6
b101 =
b101 .
b101 <
b101 G
b101 H
1'
#480000
0'
#485000
b111 #
b111 3
b111 8
b111 >
b100 $
b100 4
b100 6
b100 =
b100 .
b100 <
b100 G
b100 H
1'
#490000
0'
#495000
b110 #
b110 3
b110 8
b110 >
b11 $
b11 4
b11 6
b11 =
b11 .
b11 <
b11 G
b11 H
1'
#500000
0'
#505000
b101 #
b101 3
b101 8
b101 >
b10 $
b10 4
b10 6
b10 =
b10 .
b10 <
b10 G
b10 H
1'
#510000
0'
#515000
b100 #
b100 3
b100 8
b100 >
b1 $
b1 4
b1 6
b1 =
b1 .
b1 <
b1 G
b1 H
1'
#520000
0'
#525000
1,
b11 #
b11 3
b11 8
b11 >
b0 $
b0 4
b0 6
b0 =
b0 .
b0 <
b0 G
b0 H
1'
#530000
0'
#535000
0,
b11101 #
b11101 3
b11101 8
b11101 >
b11010 $
b11010 4
b11010 6
b11010 =
b11010 .
b11010 <
b11010 G
b11010 H
1'
#540000
0'
#545000
b11100 #
b11100 3
b11100 8
b11100 >
b11001 $
b11001 4
b11001 6
b11001 =
b11001 .
b11001 <
b11001 G
b11001 H
1'
#550000
0'
#555000
b11011 #
b11011 3
b11011 8
b11011 >
b11000 $
b11000 4
b11000 6
b11000 =
b11000 .
b11000 <
b11000 G
b11000 H
1'
#560000
0'
#565000
b11010 #
b11010 3
b11010 8
b11010 >
b10111 $
b10111 4
b10111 6
b10111 =
b10111 .
b10111 <
b10111 G
b10111 H
1'
#570000
0'
#575000
b11001 #
b11001 3
b11001 8
b11001 >
b10110 $
b10110 4
b10110 6
b10110 =
b10110 .
b10110 <
b10110 G
b10110 H
1'
#580000
0'
#585000
b11000 #
b11000 3
b11000 8
b11000 >
b10101 $
b10101 4
b10101 6
b10101 =
b10101 .
b10101 <
b10101 G
b10101 H
1'
#590000
0'
#595000
b10111 #
b10111 3
b10111 8
b10111 >
b10100 $
b10100 4
b10100 6
b10100 =
b10100 .
b10100 <
b10100 G
b10100 H
1'
#600000
0'
#605000
b10110 #
b10110 3
b10110 8
b10110 >
b10011 $
b10011 4
b10011 6
b10011 =
b10011 .
b10011 <
b10011 G
b10011 H
1'
#610000
0'
#615000
b10101 #
b10101 3
b10101 8
b10101 >
b10010 $
b10010 4
b10010 6
b10010 =
b10010 .
b10010 <
b10010 G
b10010 H
1'
#620000
b1 E
07
15
0'
1&
#625000
b10100 "
b10100 *
b10100 9
b10100 C
b10 #
b10 3
b10 8
b10 >
b10 $
b10 4
b10 6
b10 =
1/
1B
11
1@
00
0A
02
0?
b10001 .
b10001 <
b10001 G
b10001 H
b1 !
b1 )
b1 :
b1 D
1'
#630000
0'
#635000
b1 #
b1 3
b1 8
b1 >
b1 $
b1 4
b1 6
b1 =
b1 -
b1 ;
b1 J
b1 K
b11010 .
b11010 <
b11010 G
b11010 H
1'
#640000
0'
#645000
b10 E
1+
b0 #
b0 3
b0 8
b0 >
b0 $
b0 4
b0 6
b0 =
b0 -
b0 ;
b0 J
b0 K
1'
#650000
0'
#655000
0+
b100001 "
b100001 *
b100001 9
b100001 C
b11010 #
b11010 3
b11010 8
b11010 >
b11101 $
b11101 4
b11101 6
b11101 =
0/
0B
01
0@
10
1A
12
1?
b10 !
b10 )
b10 :
b10 D
b10 -
b10 ;
b10 J
b10 K
1'
#660000
0'
#665000
b11001 #
b11001 3
b11001 8
b11001 >
b11100 $
b11100 4
b11100 6
b11100 =
b11001 .
b11001 <
b11001 G
b11001 H
1'
#670000
0'
#675000
b11000 #
b11000 3
b11000 8
b11000 >
b11011 $
b11011 4
b11011 6
b11011 =
b11000 .
b11000 <
b11000 G
b11000 H
1'
#680000
0'
#685000
b10111 #
b10111 3
b10111 8
b10111 >
b11010 $
b11010 4
b11010 6
b11010 =
b10111 .
b10111 <
b10111 G
b10111 H
1'
#690000
0'
#695000
b10110 #
b10110 3
b10110 8
b10110 >
b11001 $
b11001 4
b11001 6
b11001 =
b10110 .
b10110 <
b10110 G
b10110 H
1'
#700000
0'
#705000
b10101 #
b10101 3
b10101 8
b10101 >
b11000 $
b11000 4
b11000 6
b11000 =
b10101 .
b10101 <
b10101 G
b10101 H
1'
#710000
0'
#715000
b10100 #
b10100 3
b10100 8
b10100 >
b10111 $
b10111 4
b10111 6
b10111 =
b10100 .
b10100 <
b10100 G
b10100 H
1'
#720000
0'
#725000
b10011 #
b10011 3
b10011 8
b10011 >
b10110 $
b10110 4
b10110 6
b10110 =
b10011 .
b10011 <
b10011 G
b10011 H
1'
#730000
0'
#735000
b10010 #
b10010 3
b10010 8
b10010 >
b10101 $
b10101 4
b10101 6
b10101 =
b10010 .
b10010 <
b10010 G
b10010 H
1'
#740000
0'
#745000
b10001 #
b10001 3
b10001 8
b10001 >
b10100 $
b10100 4
b10100 6
b10100 =
b10001 .
b10001 <
b10001 G
b10001 H
1'
#750000
0'
#755000
b10000 #
b10000 3
b10000 8
b10000 >
b10011 $
b10011 4
b10011 6
b10011 =
b10000 .
b10000 <
b10000 G
b10000 H
1'
#760000
0'
#765000
b1111 #
b1111 3
b1111 8
b1111 >
b10010 $
b10010 4
b10010 6
b10010 =
b1111 .
b1111 <
b1111 G
b1111 H
1'
#770000
05
0'
1%
#775000
b1110 #
b1110 3
b1110 8
b1110 >
b10001 $
b10001 4
b10001 6
b10001 =
b1110 .
b1110 <
b1110 G
b1110 H
1'
#780000
0'
#785000
b1101 #
b1101 3
b1101 8
b1101 >
b10000 $
b10000 4
b10000 6
b10000 =
b1101 .
b1101 <
b1101 G
b1101 H
1'
#790000
0'
#795000
b1100 #
b1100 3
b1100 8
b1100 >
b1111 $
b1111 4
b1111 6
b1111 =
b1100 .
b1100 <
b1100 G
b1100 H
1'
#800000
0'
#805000
b1011 #
b1011 3
b1011 8
b1011 >
b1110 $
b1110 4
b1110 6
b1110 =
b1011 .
b1011 <
b1011 G
b1011 H
1'
#810000
0'
#815000
b1010 #
b1010 3
b1010 8
b1010 >
b1101 $
b1101 4
b1101 6
b1101 =
b1010 .
b1010 <
b1010 G
b1010 H
1'
#820000
0'
#825000
b1001 #
b1001 3
b1001 8
b1001 >
b1100 $
b1100 4
b1100 6
b1100 =
b1001 .
b1001 <
b1001 G
b1001 H
1'
#830000
0'
#835000
b1000 #
b1000 3
b1000 8
b1000 >
b1011 $
b1011 4
b1011 6
b1011 =
b1000 .
b1000 <
b1000 G
b1000 H
1'
